{
	"errorCode": "0",
	"success": true,
	"fieldErrors": [],
	"msg": "请求成功！",
	"data": {
		"projectNo": "hgcsxm",
		"projectName": "回归测试项目",
		"projectAddress": "北京市/北京市",
		"groupIds": "null",
		"startTime": 1568860222000,
		"endTime": 1572489022000,
		"createTime": 1568860391000,
		"status": 1,
		"deliveryType": 1,
		"createName": "季秋李",
		"imageKey": null,
		"managerInfo": [{
			"id": 1,
			"fieldName": "项目经理",
			"value": "项目经li"
		}, {
			"id": 2,
			"fieldName": "项目总监",
			"value": "项目总jian"
		}, {
			"id": 3,
			"fieldName": "项目副总监",
			"value": "项目副总jian"
		}, {
			"id": 37,
			"fieldName": "设计主任",
			"value": null
		}, {
			"id": 54,
			"fieldName": "通信工程",
			"value": "方长年"
		}, {
			"id": 63,
			"fieldName": "只有项目策划",
			"value": "方长年"
		}],
		"designInfo": [{
			"id": 3,
			"fieldName": "项目等级",
			"value": "一般项目"
		}, {
			"id": 6,
			"fieldName": "签约情况",
			"value": "是"
		}, {
			"id": 10,
			"fieldName": "质量目标",
			"value": "顾客满意"
		}, {
			"id": 37,
			"fieldName": "项目类型",
			"value": "规划设计(城市设计,旅游用),居住建筑(高层,联),公共建筑(办公,体)"
		}, {
			"id": 41,
			"fieldName": "设计阶段",
			"value": "规划方案,初步设计,施工图设计"
		}, {
			"id": 51,
			"fieldName": "设计范围",
			"value": "规划方案"
		}, {
			"id": 65,
			"fieldName": "绿色等级",
			"value": "国际(一)"
		}, {
			"id": 72,
			"fieldName": "结构形式",
			"value": "现浇"
		}, {
			"id": 94,
			"fieldName": "交付方式",
			"value": "亲临"
		}, {
			"id": 100,
			"fieldName": "交付方式",
			"value": "1"
		}],
		"baseIds": [3, 6, 10]
	}
}